[
  {
    "id": "62b8f1e3",
    "index": 0,
    "isNews": true, 
    "brand": "Yamaha",
    "type": "Scooter",
    "capacity": 125,
    "color": "Negro",
    "thumbnail" : "./static/img/products/motorcycle.png",
    "description": "Una moto versátil y económica para ciudad.",
    "price": 2000000
  },
  {
    "id": "8d4a7b9c",
    "index": 1,
    "isNews": true, 
    "brand": "Honda",
    "type": "Deportiva",
    "capacity": 600,
    "color": "Azul",
    "thumbnail" : "./static/img/products/motorcycle.png",
    "description": "Una moto ágil y potente para carretera.",
    "price": 5000000
  },
  {
    "id": "3e2a7d9c",
    "index": 2,
    "isNews": true, 
    "brand": "Kawasaki",
    "type": "Naked",
    "capacity": 800,
    "color": "Blanco",
    "thumbnail" : "./static/img/products/motorcycle.png",
    "description": "Una moto con diseño urbano y cómodo para viajes cortos.",
    "price": 4500000
  },
  {
    "id": "5f7c8d9a",
    "index": 3,
    "isNews": true, 
    "brand": "Suzuki",
    "type": "Trail",
    "capacity": 250,
    "color": "Verde",
    "thumbnail" : "./static/img/products/motorcycle.png",
    "description": "Una moto todo terreno ideal para aventuras off-road.",
    "price": 3500000
  },
  {
    "id": "9a3b7c6d",
    "index": 4,
    "isNews": true, 
    "brand": "BMW",
    "type": "Touring",
    "capacity": 1200,
    "color": "Gris",
    "thumbnail" : "./static/img/products/motorcycle.png",
    "description": "Una moto para largos viajes con gran capacidad de carga.",
    "price": 8000000
  },
  {
    "id": "6e5d4c3b",
    "index": 5,
    "isNews": true, 
    "brand": "Ducati",
    "type": "Cafe Racer",
    "capacity": 1000,
    "color": "Rojo",
    "thumbnail" : "./static/img/products/motorcycle.png",
    "description": "Una moto estilo retro con alto rendimiento.",
    "price": 6000000
  },
  {
    "id": "2a4c5e3d",
    "index": 6,
    "isNews": true, 
    "brand": "Triumph",
    "type": "Custom",
    "capacity": 900,
    "color": "Negro Mate",
    "thumbnail" : "./static/img/products/motorcycle.png",
    "description": "Una moto con diseño clásico y personalizable.",
    "price": 7000000
  },
  {
    "id": "7d8e9f2a",
    "index": 7,
    "isNews": true, 
    "brand": "Harley-Davidson",
    "type": "Cruiser",
    "capacity": 1800,
    "color": "Plateado",
    "thumbnail" : "./static/img/products/motorcycle.png",
    "description": "Una moto icónica con potencia y estilo inconfundible.",
    "price": 12000000
  },
  {
    "id": "8b1c2d3e",
    "index": 8,
    "isNews": false, 
    "brand": "Aprilia",
    "type": "Sport Touring",
    "capacity": 1100,
    "color": "Amarillo",
    "thumbnail" : "./static/img/products/motorcycle.png",
    "description": "Una moto para viajes largos con estilo deportivo.",
    "price": 7500000
  },
  {
    "id": "3c5d2e4f",
    "index": 9,
    "isNews": false, 
    "brand": "KTM",
    "type": "Enduro",
    "capacity": 300,
    "color": "Naranja",
    "thumbnail" : "./static/img/products/motorcycle.png",
    "description": "Una moto robusta y versátil para todo tipo de terreno.",
    "price": 4000000
  },
  {
    "id": "4a5b6c7d",
    "index": 10,
    "isNews": false, 
    "brand": "Benelli",
    "type": "Scooter",
    "capacity": 150,
    "color": "Blanco",
    "thumbnail" : "./static/img/products/motorcycle.png",
    "description": "Una moto práctica y ágil para desplazamientos urbanos.",
    "price": 1800000
  },
  {
    "id": "7e8f9a1b",
    "index": 11,
    "isNews": false, 
    "brand": "Daelim",
    "type": "Cruiser",
    "capacity": 250,
    "color": "Negro",
    "thumbnail" : "./static/img/products/motorcycle.png",
    "description": "Una moto con estilo clásico y comodidad en carretera.",
    "price": 2800000
  },
  {
    "id": "9c2d3e4f",
    "index": 12,
    "isNews": false, 
    "brand": "Gas Gas",
    "type": "Enduro",
    "capacity": 300,
    "color": "Rojo",
    "thumbnail" : "./static/img/products/motorcycle.png",
    "description": "Una moto todo terreno resistente y potente.",
    "price": 3200000
  },
  {
    "id": "1a3b5c6d",
    "index": 13,
    "isNews": false, 
    "brand": "Hyosung",
    "type": "Deportiva",
    "capacity": 250,
    "color": "Azul",
    "thumbnail" : "./static/img/products/motorcycle.png",
    "description": "Una moto ágil y divertida para carretera.",
    "price": 2500000
  },
  {
    "id": "4e5f6a7b",
    "index": 14,
    "isNews": false, 
    "brand": "Indian",
    "type": "Cruiser",
    "capacity": 1800,
    "color": "Negro",
    "thumbnail" : "./static/img/products/motorcycle.png",
    "description": "Una moto con diseño clásico y prestaciones modernas.",
    "price": 11000000
  },
  {
    "id": "8d9a1b2c",
    "index": 15,
    "isNews": false, 
    "brand": "Kawasaki",
    "type": "Naked",
    "capacity": 650,
    "color": "Verde",
    "thumbnail" : "./static/img/products/motorcycle.png",
    "description": "Una moto versátil y deportiva para uso diario.",
    "price": 4800000
  },
  {
    "id": "3b4c5d6e",
    "index": 16,
    "isNews": false, 
    "brand": "KTM",
    "type": "Adventure",
    "capacity": 1290,
    "color": "Naranja",
    "thumbnail" : "./static/img/products/motorcycle.png",
    "description": "Una moto para aventuras extremas en cualquier terreno.",
    "price": 8500000
  },
  {
    "id": "6a7b8c9d",
    "index": 17,
    "isNews": false, 
    "brand": "Moto Guzzi",
    "type": "Custom",
    "capacity": 850,
    "color": "Negro",
    "thumbnail" : "./static/img/products/motorcycle.png",
    "description": "Una moto con diseño clásico y confortable para largos viajes.",
    "price": 7200000
  },
  {
    "id": "5c6d7e8f",
    "index": 18,
    "isNews": false, 
    "brand": "MV Agusta",
    "type": "Sport",
    "capacity": 800,
    "color": "Rojo",
    "thumbnail" : "./static/img/products/motorcycle.png",
    "description": "Una moto deportiva con diseño elegante y alto rendimiento.",
    "price": 8800000
  },
  {
    "id": "1b2c3d4e",
    "index": 19,
    "isNews": false, 
    "brand": "Norton",
    "type": "Cafe Racer",
    "capacity": 900,
    "color": "Negro Mate",
    "thumbnail" : "./static/img/products/motorcycle.png",
    "description": "Una moto estilo retro con modernas prestaciones.",
    "price": 6900000
  },
  {
    "id": "2c3d4e5f",
    "index": 20,
    "isNews": false, 
    "brand": "Royal Enfield",
    "type": "Classic",
    "capacity": 500,
    "color": "Verde Militar",
    "thumbnail" : "./static/img/products/motorcycle.png",
    "description": "Una moto clásica con estilo vintage y fiabilidad.",
    "price": 3000000
  },
  {
    "id": "4d5e6f7a",
    "index": 21,
    "isNews": false, 
    "brand": "SWM",
    "type": "Adventure",
    "capacity": 600,
    "color": "Blanco",
    "thumbnail" : "./static/img/products/motorcycle.png",
    "description": "Una moto versátil y ágil para todo tipo de terreno.",
    "price": 3800000
  },
  {
    "id": "7e8f9a1b",
    "index": 22,
    "isNews": false, 
    "brand": "SYM",
    "type": "Scooter",
    "capacity": 200,
    "color": "Rojo",
    "thumbnail" : "./static/img/products/motorcycle.png",
    "description": "Una moto práctica y cómoda para desplazamientos urbanos.",
    "price": 2200000
  },
  {
    "id": "9a1b2c3d",
    "index": 23,
    "isNews": false, 
    "brand": "Vespa",
    "type": "Scooter",
    "capacity": 150,
    "color": "Gris",
    "thumbnail" : "./static/img/products/motorcycle.png",
    "description": "Una moto clásica con estilo urbano y elegancia.",
    "price": 2800000
  },
  {
    "id": "1b2c3d4e",
    "index": 24,
    "isNews": false, 
    "brand": "Zero",
    "type": "Electric",
    "capacity": 1000,
    "color": "Negro",
    "thumbnail" : "./static/img/products/motorcycle.png",
    "description": "Una moto eléctrica con tecnología avanzada y rendimiento.",
    "price": 9000000
  },
  {
    "id": "2c3d4e5f",
    "index": 25,
    "isNews": false, 
    "brand": "BMW",
    "type": "Maxi Scooter",
    "capacity": 650,
    "color": "Blanco",
    "thumbnail" : "./static/img/products/motorcycle.png",
    "description": "Una moto cómoda y versátil para viajes largos.",
    "price": 5500000
  },
  {
    "id": "3d4e5f6a",
    "index": 26,
    "isNews": false, 
    "brand": "Harley-Davidson",
    "type": "Touring",
    "capacity": 1600,
    "color": "Negro",
    "thumbnail" : "./static/img/products/motorcycle.png",
    "description": "Una moto para viajes largos con estilo y confort.",
    "price": 11000000
  },
  {
    "id": "4e5f6a7b",
    "index": 27,
    "isNews": false, 
    "brand": "Indian",
    "type": "Cruiser",
    "capacity": 2000,
    "color": "Rojo",
    "thumbnail" : "./static/img/products/motorcycle.png",
    "description": "Una moto con diseño clásico y potencia impresionante.",
    "price": 15000000
  },
  {
    "id": "5f6a7b8c",
    "index": 28,
    "isNews": false, 
    "brand": "Kawasaki",
    "type": "Superbike",
    "capacity": 1000,
    "color": "Verde",
    "thumbnail" : "./static/img/products/motorcycle.png",
    "description": "Una moto de alta velocidad y rendimiento en pista.",
    "price": 12000000
  },
  {
    "id": "6a7b8c9d",
    "index": 29,
    "isNews": false, 
    "brand": "KTM",
    "type": "Supermoto",
    "capacity": 690,
    "color": "Naranja",
    "thumbnail" : "./static/img/products/motorcycle.png",
    "description": "Una moto ágil y versátil para carretera y off-road.",
    "price": 6000000
  },
  {
    "id": "7b8c9d1e",
    "index": 30,
    "isNews": false, 
    "brand": "Moto Guzzi",
    "type": "Adventure",
    "capacity": 850,
    "color": "Negro",
    "thumbnail" : "./static/img/products/motorcycle.png",
    "description": "Una moto versátil y cómoda para largas rutas.",
    "price": 8000000
  },
  {
    "id": "8c9d1e2f",
    "index": 31,
    "isNews": false, 
    "brand": "Suzuki",
    "type": "Cafe Racer",
    "capacity": 750,
    "color": "Azul",
    "thumbnail" : "./static/img/products/motorcycle.png",
    "description": "Una moto con estilo retro y prestaciones modernas.",
    "price": 5800000
  },
  {
    "id": "9d1e2f3a",
    "index": 32,
    "isNews": false, 
    "brand": "Triumph",
    "type": "Street Triple",
    "capacity": 765,
    "color": "Blanco",
    "thumbnail" : "./static/img/products/motorcycle.png",
    "description": "Una moto naked deportiva con diseño agresivo.",
    "price": 7200000
  },
  {
    "id": "1e2f3a4b",
    "index": 33,
    "isNews": false, 
    "brand": "Yamaha",
    "type": "Hyper Naked",
    "capacity": 1000,
    "color": "Negro",
    "thumbnail" : "./static/img/products/motorcycle.png",
    "description": "Una moto naked con alto rendimiento y estilo urbano.",
    "price": 8400000
  },
  {
    "id": "2f3a4b5c",
    "index": 34,
    "isNews": false, 
    "brand": "Ducati",
    "type": "Scrambler",
    "capacity": 800,
    "color": "Amarillo",
    "thumbnail" : "./static/img/products/motorcycle.png",
    "description": "Una moto versátil y divertida para todo tipo de terreno.",
    "price": 6900000
  },
  {
    "id": "3a4b5c6d",
    "index": 35,
    "isNews": false, 
    "brand": "Kawasaki",
    "type": "Z",
    "capacity": 900,
    "color": "Verde",
    "thumbnail" : "./static/img/products/motorcycle.png",
    "description": "Una moto naked con diseño agresivo y alto rendimiento.",
    "price": 7500000
  },
  {
    "id": "4b5c6d7e",
    "index": 36,
    "isNews": false, 
    "brand": "KTM",
    "type": "Duke",
    "capacity": 790,
    "color": "Naranja",
    "thumbnail" : "./static/img/products/motorcycle.png",
    "description": "Una moto naked con tecnología avanzada y rendimiento deportivo.",
    "price": 6800000
  },
  {
    "id": "5c6d7e8f",
    "index": 37,
    "isNews": false, 
    "brand": "Suzuki",
    "type": "SV",
    "capacity": 650,
    "color": "Azul",
    "thumbnail" : "./static/img/products/motorcycle.png",
    "description": "Una moto naked versátil y cómoda para ciudad y carretera.",
    "price": 5000000
  },
  {
    "id": "6d7e8f9a",
    "index": 38,
    "isNews": false, 
    "brand": "Yamaha",
    "type": "MT",
    "capacity": 850,
    "color": "Negro",
    "thumbnail" : "./static/img/products/motorcycle.png",
    "description": "Una moto naked con diseño agresivo y alto rendimiento.",
    "price": 7800000
  },
  {
    "id": "7e8f9a1b",
    "index": 39,
    "isNews": false, 
    "brand": "Honda",
    "type": "CB",
    "capacity": 650,
    "color": "Rojo",
    "thumbnail" : "./static/img/products/motorcycle.png",
    "description": "Una moto naked versátil y cómoda para ciudad y carretera.",
    "price": 5500000
  },
  {
    "id": "8f9a1b2c",
    "index": 40,
    "isNews": false, 
    "brand": "Kawasaki",
    "type": "Vulcan",
    "capacity": 650,
    "color": "Negro",
    "thumbnail" : "./static/img/products/motorcycle.png",
    "description": "Una moto cruiser con estilo clásico y confortable.",
    "price": 6200000
  },
  {
    "id": "9a1b2c3d",
    "index": 41,
    "isNews": false, 
    "brand": "Harley-Davidson",
    "type": "Softail",
    "capacity": 1700,
    "color": "Plateado",
    "thumbnail" : "./static/img/products/motorcycle.png",
    "description": "Una moto cruiser con diseño clásico y tecnología moderna.",
    "price": 11000000
  },
  {
    "id": "1b2c3d4e",
    "index": 42,
    "isNews": false, 
    "brand": "Indian",
    "type": "Chief",
    "capacity": 1800,
    "color": "Negro",
    "thumbnail" : "./static/img/products/motorcycle.png",
    "description": "Una moto cruiser con estilo clásico y prestaciones modernas.",
    "price": 12000000
  },
  {
    "id": "2c3d4e5f",
    "index": 43,
    "isNews": false, 
    "brand": "Moto Guzzi",
    "type": "V7",
    "capacity": 750,
    "color": "Azul",
    "thumbnail" : "./static/img/products/motorcycle.png",
    "description": "Una moto con estilo retro y confortable para viajes cortos.",
    "price": 6500000
  },
  {
    "id": "3d4e5f6a",
    "index": 44,
    "isNews": false, 
    "brand": "Triumph",
    "type": "Speed Triple",
    "capacity": 1050,
    "color": "Blanco",
    "thumbnail" : "./static/img/products/motorcycle.png",
    "description": "Una moto naked con alto rendimiento y estilo deportivo.",
    "price": 8400000
  },
  {
    "id": "4e5f6a7b",
    "index": 45,
    "isNews": false, 
    "brand": "Yamaha",
    "type": "Tracer",
    "capacity": 900,
    "color": "Rojo",
    "thumbnail" : "./static/img/products/motorcycle.png",
    "description": "Una moto sport touring versátil y cómoda para largas rutas.",
    "price": 7800000
  },
  {
    "id": "5f6a7b8c",
    "index": 46,
    "isNews": false, 
    "brand": "Ducati",
    "type": "Multistrada",
    "capacity": 1260,
    "color": "Amarillo",
    "thumbnail" : "./static/img/products/motorcycle.png",
    "description": "Una moto touring con tecnología avanzada y confort.",
    "price": 11000000
  },
  {
    "id": "6a7b8c9d",
    "index": 47,
    "isNews": false, 
    "brand": "Kawasaki",
    "type": "Versys",
    "capacity": 1000,
    "color": "Verde",
    "thumbnail" : "./static/img/products/motorcycle.png",
    "description": "Una moto adventure touring para viajes largos y variedad de terrenos.",
    "price": 8500000
  },
  {
    "id": "7b8c9d1e",
    "index": 48,
    "isNews": false, 
    "brand": "BMW",
    "type": "GS",
    "capacity": 1250,
    "color": "Negro",
    "thumbnail" : "./static/img/products/motorcycle.png",
    "description": "Una moto para aventuras extremas en todo tipo de terreno.",
    "price": 13500000
  },
  {
    "id": "8c9d1e2f",
    "index": 49,
    "isNews": false, 
    "brand": "Harley-Davidson",
    "type": "Road King",
    "capacity": 1750,
    "color": "Negro",
    "thumbnail" : "./static/img/products/motorcycle.png",
    "description": "Una moto touring con estilo clásico y confort moderno.",
    "price": 12500000
  },
  {
    "id": "9d1e2f3a",
    "index": 50,
    "isNews": false, 
    "brand": "Indian",
    "type": "Challenger",
    "capacity": 1800,
    "color": "Rojo",
    "thumbnail" : "./static/img/products/motorcycle.png",
    "description": "Una moto touring con estilo clásico y tecnología avanzada.",
    "price": 13000000
  },
  {
    "id": "1e2f3a4b",
    "index": 51,
    "isNews": false, 
    "brand": "Triumph",
    "type": "Rocket",
    "capacity": 2500,
    "color": "Negro",
    "thumbnail" : "./static/img/products/motorcycle.png",
    "description": "Una moto cruiser con potencia impresionante y diseño exclusivo.",
    "price": 15000000
  },
  {
    "id": "2f3a4b5c",
    "index": 52,
    "isNews": false, 
    "brand": "Yamaha",
    "type": "VMAX",
    "capacity": 1700,
    "color": "Gris",
    "thumbnail" : "./static/img/products/motorcycle.png",
    "description": "Una moto power cruiser con rendimiento y estilo excepcionales.",
    "price": 14000000
  },
  {
    "id": "3a4b5c6d",
    "index": 53,
    "isNews": false, 
    "brand": "BMW",
    "type": "S",
    "capacity": 1000,
    "color": "Blanco",
    "thumbnail" : "./static/img/products/motorcycle.png",
    "description": "Una moto sport touring con alto rendimiento y tecnología.",
    "price": 9500000
  },
  {
    "id": "4b5c6d7e",
    "index": 54,
    "isNews": false, 
    "brand": "Ducati",
    "type": "Panigale",
    "capacity": 1000,
    "color": "Rojo",
    "thumbnail" : "./static/img/products/motorcycle.png",
    "description": "Una moto superbike con tecnología de competición y alto rendimiento.",
    "price": 16000000
  },
  {
    "id": "5c6d7e8f",
    "index": 55,
    "isNews": false, 
    "brand": "Harley-Davidson",
    "type": "Fat Boy",
    "capacity": 1800,
    "color": "Negro",
    "thumbnail" : "./static/img/products/motorcycle.png",
    "description": "Una moto cruiser icónica con estilo y potencia.",
    "price": 13500000
  },
  {
    "id": "6d7e8f9a",
    "index": 56,
    "isNews": false, 
    "brand": "Honda",
    "type": "Gold Wing",
    "capacity": 1800,
    "color": "Amarillo",
    "thumbnail" : "./static/img/products/motorcycle.png",
    "description": "Una moto touring de lujo con tecnología y confort incomparables.",
    "price": 17000000
  },
  {
    "id": "7e8f9a1b",
    "index": 57,
    "isNews": false, 
    "brand": "Kawasaki",
    "type": "Ninja",
    "capacity": 1000,
    "color": "Verde",
    "thumbnail" : "./static/img/products/motorcycle.png",
    "description": "Una moto sport con diseño agresivo y prestaciones de pista.",
    "price": 14500000
  },
  {
    "id": "8f9a1b2c",
    "index": 58,
    "isNews": false, 
    "brand": "Suzuki",
    "type": "Hayabusa",
    "capacity": 1300,
    "color": "Azul",
    "thumbnail" : "./static/img/products/motorcycle.png",
    "description": "Una moto sport touring con altas velocidades y confort.",
    "price": 16000000
  },
  {
    "id": "9a1b2c3d",
    "index": 59,
    "isNews": false, 
    "brand": "Yamaha",
    "type": "R1",
    "capacity": 1000,
    "color": "Blanco",
    "thumbnail" : "./static/img/products/motorcycle.png",
    "description": "Una moto superbike con tecnología de competición y rendimiento extremo.",
    "price": 18000000
  },
  {
    "id": "1b2c3d4e",
    "index": 60,
    "isNews": false, 
    "brand": "Aprilia",
    "type": "RSV4",
    "capacity": 1000,
    "color": "Negro",
    "thumbnail" : "./static/img/products/motorcycle.png",
    "description": "Una moto de competición con tecnología avanzada y rendimiento excepcional.",
    "price": 17000000
  },
  {
    "id": "2c3d4e5f",
    "index": 61,
    "isNews": false, 
    "brand": "BMW",
    "type": "S1000RR",
    "capacity": 1000,
    "color": "Gris",
    "thumbnail" : "./static/img/products/motorcycle.png",
    "description": "Una moto de competición con tecnología avanzada y altas velocidades.",
    "price": 19000000
  },
  {
    "id": "3d4e5f6a",
    "index": 62,
    "isNews": false, 
    "brand": "Ducati",
    "type": "Panigale V4",
    "capacity": 1100,
    "color": "Rojo",
    "thumbnail" : "./static/img/products/motorcycle.png",
    "description": "Una moto de competición con tecnología avanzada y prestaciones de pista.",
    "price": 22000000
  },
  {
    "id": "4e5f6a7b",
    "index": 63,
    "isNews": false, 
    "brand": "Honda",
    "type": "CBR",
    "capacity": 1000,
    "color": "Azul",
    "thumbnail" : "./static/img/products/motorcycle.png",
    "description": "Una moto de competición con diseño aerodinámico y altas velocidades.",
    "price": 20000000
  },
  {
    "id": "5f6a7b8c",
    "index": 64,
    "isNews": false, 
    "brand": "Kawasaki",
    "type": "ZX-10R",
    "capacity": 1000,
    "color": "Verde",
    "thumbnail" : "./static/img/products/motorcycle.png",
    "description": "Una moto de competición con tecnología de punta y prestaciones extremas.",
    "price": 21000000
  },
  {
    "id": "6a7b8c9d",
    "index": 65,
    "isNews": false, 
    "brand": "Suzuki",
    "type": "GSX-R",
    "capacity": 1000,
    "color": "Negro",
    "thumbnail" : "./static/img/products/motorcycle.png",
    "description": "Una moto de competición con diseño agresivo y alto rendimiento.",
    "price": 19000000
  },
  {
    "id": "7b8c9d1e",
    "index": 66,
    "isNews": false, 
    "brand": "Yamaha",
    "type": "YZF-R1M",
    "capacity": 1000,
    "color": "Blanco",
    "thumbnail" : "./static/img/products/motorcycle.png",
    "description": "Una moto de competición con tecnología avanzada y rendimiento excepcional.",
    "price": 24000000
  },
  {
    "id": "8c9d1e2f",
    "index": 67,
    "isNews": false, 
    "brand": "KTM",
    "type": "RC",
    "capacity": 390,
    "color": "Naranja",
    "thumbnail" : "./static/img/products/motorcycle.png",
    "description": "Una moto de competición con diseño deportivo y agilidad.",
    "price": 9000000
  },
  {
    "id": "9d1e2f3a",
    "index": 68,
    "isNews": false, 
    "brand": "Triumph",
    "type": "Daytona",
    "capacity": 765,
    "color": "Blanco",
    "thumbnail" : "./static/img/products/motorcycle.png",
    "description": "Una moto de competición con diseño aerodinámico y alto rendimiento.",
    "price": 13000000
  },
  {
    "id": "1e2f3a4b",
    "index": 69,
    "isNews": false, 
    "brand": "Yamaha",
    "type": "YZF-R6",
    "capacity": 600,
    "color": "Azul",
    "thumbnail" : "./static/img/products/motorcycle.png",
    "description": "Una moto de competición con diseño deportivo y agilidad.",
    "price": 15000000
  },
  {
    "id": "2f3a4b5c",
    "index": 70,
    "isNews": false, 
    "brand": "Ducati",
    "type": "848",
    "capacity": 849,
    "color": "Amarillo",
    "thumbnail" : "./static/img/products/motorcycle.png",
    "description": "Una moto de competición con diseño deportivo y alto rendimiento.",
    "price": 18000000
  },
  {
    "id": "3a4b5c6d",
    "index": 71,
    "isNews": false, 
    "brand": "Kawasaki",
    "type": "Ninja H2",
    "capacity": 1000,
    "color": "Verde",
    "thumbnail" : "./static/img/products/motorcycle.png",
    "description": "Una moto de competición con diseño agresivo y potencia extrema.",
    "price": 30000000
  },
  {
    "id": "4b5c6d7e",
    "index": 72,
    "isNews": false, 
    "brand": "KTM",
    "type": "RC8",
    "capacity": 1195,
    "color": "Naranja",
    "thumbnail" : "./static/img/products/motorcycle.png",
    "description": "Una moto de competición con diseño agresivo y alto rendimiento.",
    "price": 25000000
  },
  {
    "id": "5c6d7e8f",
    "index": 73,
    "isNews": false, 
    "brand": "Suzuki",
    "type": "GSX-R1000R",
    "capacity": 1000,
    "color": "Azul",
    "thumbnail" : "./static/img/products/motorcycle.png",
    "description": "Una moto de competición con diseño aerodinámico y potencia excepcional.",
    "price": 26000000
  },
  {
    "id": "6d7e8f9a",
    "index": 74,
    "isNews": false, 
    "brand": "Yamaha",
    "type": "YZF-R1S",
    "capacity": 1000,
    "color": "Blanco",
    "thumbnail" : "./static/img/products/motorcycle.png",
    "description": "Una moto de competición con diseño deportivo y alto rendimiento.",
    "price": 23000000
  },
  {
    "id": "7e8f9a1b",
    "index": 75,
    "isNews": false, 
    "brand": "Honda",
    "type": "CBR1000RR",
    "capacity": 1000,
    "color": "Rojo",
    "thumbnail" : "./static/img/products/motorcycle.png",
    "description": "Una moto de competición con diseño agresivo y prestaciones de pista.",
    "price": 28000000
  },
  {
    "id": "8f9a1b2c",
    "index": 76,
    "isNews": false, 
    "brand": "Kawasaki",
    "type": "Ninja ZX-14R",
    "capacity": 1400,
    "color": "Negro",
    "thumbnail" : "./static/img/products/motorcycle.png",
    "description": "Una moto de competición con diseño aerodinámico y altas velocidades.",
    "price": 32000000
  },
  {
    "id": "9a1b2c3d",
    "index": 77,
    "isNews": false, 
    "brand": "Suzuki",
    "type": "GSX-S1000F",
    "capacity": 1000,
    "color": "Negro",
    "thumbnail" : "./static/img/products/motorcycle.png",
    "description": "Una moto sport touring con diseño agresivo y alto rendimiento.",
    "price": 24000000
  },
  {
    "id": "1b2c3d4e",
    "index": 78,
    "isNews": false, 
    "brand": "Yamaha",
    "type": "FJR1300",
    "capacity": 1300,
    "color": "Negro",
    "thumbnail" : "./static/img/products/motorcycle.png",
    "description": "Una moto sport touring con tecnología avanzada y confort.",
    "price": 27000000
  },
  {
    "id": "2c3d4e5f",
    "index": 79,
    "isNews": false, 
    "brand": "BMW",
    "type": "K1600GT",
    "capacity": 1600,
    "color": "Negro",
    "thumbnail" : "./static/img/products/motorcycle.png",
    "description": "Una moto touring de lujo con tecnología y confort excepcionales.",
    "price": 35000000
  },
  {
    "id": "3d4e5f6a",
    "index": 80,
    "isNews": false, 
    "brand": "Ducati",
    "type": "Diavel",
    "capacity": 1260,
    "color": "Negro",
    "thumbnail" : "./static/img/products/motorcycle.png",
    "description": "Una moto cruiser deportiva con diseño agresivo y tecnología avanzada.",
    "price": 30000000
  },
  {
    "id": "4e5f6a7b",
    "index": 81,
    "isNews": false, 
    "brand": "Harley-Davidson",
    "type": "Street Glide",
    "capacity": 1750,
    "color": "Negro",
    "thumbnail" : "./static/img/products/motorcycle.png",
    "description": "Una moto touring con diseño clásico y tecnología moderna.",
    "price": 38000000
  },
  {
    "id": "5f6a7b8c",
    "index": 82,
    "isNews": false, 
    "brand": "Honda",
    "type": "Gold Wing Tour",
    "capacity": 1800,
    "color": "Rojo",
    "thumbnail" : "./static/img/products/motorcycle.png",
    "description": "Una moto touring de lujo con tecnología y confort excepcionales.",
    "price": 42000000
  },
  {
    "id": "6a7b8c9d",
    "index": 83,
    "isNews": false, 
    "brand": "Indian",
    "type": "Chieftain",
    "capacity": 1800,
    "color": "Gris",
    "thumbnail" : "./static/img/products/motorcycle.png",
    "description": "Una moto cruiser con estilo clásico y prestaciones modernas.",
    "price": 37000000
  },
  {
    "id": "7b8c9d1e",
    "index": 84,
    "isNews": false, 
    "brand": "Kawasaki",
    "type": "Vulcan S",
    "capacity": 650,
    "color": "Negro",
    "thumbnail" : "./static/img/products/motorcycle.png",
    "description": "Una moto cruiser versátil y cómoda para uso diario.",
    "price": 7000000
  },
  {
    "id": "8c9d1e2f",
    "index": 85,
    "isNews": false, 
    "brand": "Suzuki",
    "type": "Boulevard",
    "capacity": 800,
    "color": "Blanco",
    "thumbnail" : "./static/img/products/motorcycle.png",
    "description": "Una moto cruiser con diseño clásico y confort moderno.",
    "price": 9500000
  },
  {
    "id": "9d1e2f3a",
    "index": 86,
    "isNews": false, 
    "brand": "Yamaha",
    "type": "XSR700",
    "capacity": 700,
    "color": "Negro",
    "thumbnail" : "./static/img/products/motorcycle.png",
    "description": "Una moto estilo retro con tecnología avanzada y rendimiento.",
    "price": 6700000
  },
  {
    "id": "1e2f3a4b",
    "index": 87,
    "isNews": false, 
    "brand": "Aprilia",
    "type": "Tuono",
    "capacity": 1100,
    "color": "Rojo",
    "thumbnail" : "./static/img/products/motorcycle.png",
    "description": "Una moto naked con alto rendimiento y diseño deportivo.",
    "price": 9800000
  },
  {
    "id": "2f3a4b5c",
    "index": 88,
    "isNews": false, 
    "brand": "BMW",
    "type": "R",
    "capacity": 1250,
    "color": "Negro",
    "thumbnail" : "./static/img/products/motorcycle.png",
    "description": "Una moto cruiser con diseño clásico y tecnología moderna.",
    "price": 11500000
  },
  {
    "id": "3a4b5c6d",
    "index": 89,
    "isNews": false, 
    "brand": "KTM",
    "type": "Super Duke",
    "capacity": 1301,
    "color": "Naranja",
    "thumbnail" : "./static/img/products/motorcycle.png",
    "description": "Una moto naked con alto rendimiento y diseño agresivo.",
    "price": 13000000
  },
  {
    "id": "4b5c6d7e",
    "index": 90,
    "isNews": false, 
    "brand": "Suzuki",
    "type": "V-Strom",
    "capacity": 650,
    "color": "Amarillo",
    "thumbnail" : "./static/img/products/motorcycle.png",
    "description": "Una moto adventure con versatilidad y confort para largos viajes.",
    "price": 8500000
  },
  {
    "id": "5c6d7e8f",
    "index": 91,
    "isNews": false, 
    "brand": "Triumph",
    "type": "Tiger",
    "capacity": 1200,
    "color": "Blanco",
    "thumbnail" : "./static/img/products/motorcycle.png",
    "description": "Una moto adventure touring con tecnología y confort.",
    "price": 11000000
  },
  {
    "id": "6d7e8f9a",
    "index": 92,
    "isNews": false, 
    "brand": "Yamaha",
    "type": "Tracer 900",
    "capacity": 900,
    "color": "Rojo",
    "thumbnail" : "./static/img/products/motorcycle.png",
    "description": "Una moto sport touring con diseño agresivo y confort para largas rutas.",
    "price": 12500000
  },
  {
    "id": "7e8f9a1b",
    "index": 93,
    "isNews": false, 
    "brand": "Honda",
    "type": "Africa Twin",
    "capacity": 1100,
    "color": "Negro",
    "thumbnail" : "./static/img/products/motorcycle.png",
    "description": "Una moto adventure con tecnología y confort para viajes off-road.",
    "price": 15000000
  },
  {
    "id": "8f9a1b2c",
    "index": 94,
    "isNews": false, 
    "brand": "Kawasaki",
    "type": "Versys-X",
    "capacity": 300,
    "color": "Negro",
    "thumbnail" : "./static/img/products/motorcycle.png",
    "description": "Una moto adventure versátil y cómoda para desplazamientos urbanos.",
    "price": 6000000
  },
  {
    "id": "9a1b2c3d",
    "index": 95,
    "isNews": false, 
    "brand": "Suzuki",
    "type": "DR-Z",
    "capacity": 400,
    "color": "Negro",
    "thumbnail" : "./static/img/products/motorcycle.png",
    "description": "Una moto dual-purpose versátil para aventuras off-road.",
    "price": 7500000
  },
  {
    "id": "1b2c3d4e",
    "index": 96,
    "isNews": false, 
    "brand": "Yamaha",
    "type": "Tenere",
    "capacity": 700,
    "color": "Blanco",
    "thumbnail" : "./static/img/products/motorcycle.png",
    "description": "Una moto dual-purpose con diseño aventurero y tecnología off-road.",
    "price": 9500000
  },
  {
    "id": "2c3d4e5f",
    "index": 97,
    "isNews": false, 
    "brand": "BMW",
    "type": "R1250GS",
    "capacity": 1250,
    "color": "Negro",
    "thumbnail" : "./static/img/products/motorcycle.png",
    "description": "Una moto dual-purpose con diseño aventurero y tecnología avanzada.",
    "price": 13500000
  },
  {
    "id": "3d4e5f6a",
    "index": 98,
    "isNews": false, 
    "brand": "KTM",
    "type": "Adventure",
    "capacity": 1290,
    "color": "Naranja",
    "thumbnail" : "./static/img/products/motorcycle.png",
    "description": "Una moto dual-purpose con tecnología off-road y confort para largos viajes.",
    "price": 14000000
  },
  {
    "id": "4e5f6a7b",
    "index": 99,
    "isNews": false, 
    "brand": "Honda",
    "type": "CRF",
    "capacity": 450,
    "color": "Rojo",
    "thumbnail" : "./static/img/products/motorcycle.png",
    "description": "Una moto off-road con tecnología avanzada y rendimiento off-road.",
    "price": 9000000
  }
]
